create_github_repo/__init__.py
create_github_repo/__main__.py
create_github_repo-0.0.5.dist-info/METADATA
create_github_repo-0.0.5.dist-info/WHEEL
create_github_repo-0.0.5.dist-info/licenses/LICENSE
create_github_repo-0.0.5.dist-info/RECORD
