Metadata-Version: 2.1
Name: create_github_repo
Version: 0.0.5
Summary: Simple CLI to initialize repos on GitHub.
Project-URL: Homepage, https://github.com/geocoug/create-github-repo
Project-URL: Bug Tracker, https://github.com/geocoug/create-github-repo/issues
Author-email: Caleb Grant <grantcaleb22@gmail.com>
License:                     GNU GENERAL PUBLIC LICENSE
Classifier: License :: OSI Approved :: MIT License
Classifier: Operating System :: OS Independent
Classifier: Programming Language :: Python :: 3
Requires-Python: >=3.7
